navamai/.DS_Store
navamai/__init__.py
navamai/action_intents.py
navamai/auditor.py
navamai/bedrock.py
navamai/claude.py
navamai/cli.py
navamai/code.py
navamai/configure.py
navamai/evaluate.py
navamai/gather.py
navamai/gemini.py
navamai/generate.py
navamai/groq.py
navamai/images.py
navamai/markdown.py
navamai/metrics.py
navamai/model_text.py
navamai/model_vision.py
navamai/ollama.py
navamai/openai.py
navamai/perplexity.py
navamai/provider.py
navamai/reference.py
navamai/scaffold/Code/article-scraper.md
navamai/scaffold/Code/navamai-main-app.md
navamai/scaffold/Code/startup-expense-manager-expense-manager.md
navamai/scaffold/Images/Generated/paint-a-star-in-ocean.png
navamai/scaffold/Images/hackathon.jpg
navamai/scaffold/Images/london-skyline.webp
navamai/scaffold/Intents/Event Planning.md
navamai/scaffold/Intents/Financial Analysis.md
navamai/scaffold/Intents/Product Management.md
navamai/scaffold/Prompts/Analyze/Extract Tips.md
navamai/scaffold/Prompts/Apps/Create Streamlit App.md
navamai/scaffold/Prompts/Apps/Create Vite App.md
navamai/scaffold/Prompts/Charts/Mermaid Topic Visualization.md
navamai/scaffold/Prompts/Images/Artist Assistant.md
navamai/scaffold/Prompts/Invest/Stock Analysis.md
navamai/scaffold/Prompts/Invest/Table of Top Stocks.md
navamai/scaffold/Prompts/NavamAI/Docs App.md
navamai/scaffold/Prompts/NavamAI/Module App.md
navamai/scaffold/Prompts/Tables/Table of Planets.md
navamai/scaffold/navamai.yml
navamai/scaffold/trail.yml
navamai/utils.py
navamai/validation.py
navamai-0.1.66.dist-info/LICENSE
navamai-0.1.66.dist-info/METADATA
navamai-0.1.66.dist-info/WHEEL
navamai-0.1.66.dist-info/entry_points.txt
navamai-0.1.66.dist-info/RECORD
