Metadata-Version: 2.1
Name: navamai
Version: 0.1.66
Summary: Use NavamAI to supercharge your productivity and workflow with personal, fast, and quality AI. Turn your Terminal into a configurable, interactive, and unobtrusive personal AI app. Power of 15 LLMs and 7 providers at your finger tips. Pair with workflows in Markdown, VS Code, Obsidian, and GitHub. Get productive fast with three simple commands.
Home-page: https://www.navamai.com
License: Apache-2.0
Author: NavamAI
Author-email: team@navamai.com
Requires-Python: >=3.12,<4.0
Classifier: License :: OSI Approved :: Apache Software License
Classifier: Programming Language :: Python :: 3
Classifier: Programming Language :: Python :: 3.12
Requires-Dist: anthropic (>=0.34.1,<0.35.0)
Requires-Dist: beautifulsoup4 (>=4.12.3,<5.0.0)
Requires-Dist: boto3 (>=1.35.13,<2.0.0)
Requires-Dist: chardet (>=5.2.0,<6.0.0)
Requires-Dist: click (>=8.1.7,<9.0.0)
Requires-Dist: google-api-python-client (>=2.142.0,<3.0.0)
Requires-Dist: google-generativeai (>=0.7.2,<0.8.0)
Requires-Dist: groq (>=0.9.0,<0.10.0)
Requires-Dist: html2text (>=2024.2.26,<2025.0.0)
Requires-Dist: lxml[html-clean] (>=4.6.3,<5.0.0)
Requires-Dist: markdown2 (>=2.5.0,<3.0.0)
Requires-Dist: openai (>=1.42.0,<2.0.0)
Requires-Dist: opencv-python (>=4.8.0,<5.0.0)
Requires-Dist: pillow (>=10.4.0,<11.0.0)
Requires-Dist: plotext (>=5.2.8,<6.0.0)
Requires-Dist: pyyaml (>=6.0.2,<7.0.0)
Requires-Dist: readability-lxml (>=0.8.1,<0.9.0)
Requires-Dist: requests (>=2.32.3,<3.0.0)
Requires-Dist: rich (>=13.7.1,<14.0.0)
Requires-Dist: robotexclusionrulesparser (>=1.7.1,<2.0.0)
Requires-Dist: term-image (>=0.7.2,<0.8.0)
